<?xml version="1.0" encoding="UTF-8" standalone="yes"?>
<configuracao>
    <issueDefault>23152345</issueDefault>
    <loginAplicacao>fulano.ciclano</loginAplicacao>
    <passwordAplicacao>123456</passwordAplicacao>
    <proxyHost>proxyteste</proxyHost>
    <proxyPassword>12345</proxyPassword>
    <proxyPort>80</proxyPort>
    <proxyUser>fulanoc</proxyUser>
    <urlPlanilha>\\CORPS031\desenvolvimento\PlanilhasHora\Fábrica\Renato Ribeiro de Paula\RENATO PAULA - PLANILHA DE PONTO-2017-03.xlsx</urlPlanilha>
    <controleHorasClass>workhourscontrol.service.impl.ControleHorasHttpImpl</controleHorasClass>
</configuracao>
